dist_alxs
