Metadata-Version: 2.1
Name: dist-alxs
Version: 0.1
Summary: Gaussian and Binomial distributions
Home-page: UNKNOWN
Author-email: mihajlovic.aleksa@gmail.com
License: UNKNOWN
Platform: UNKNOWN
